prefix_tree/__init__.py
prefix_tree/trie.py
prefix_tree-0.0.8.dist-info/licenses/LICENSE
prefix_tree-0.0.8.dist-info/METADATA
prefix_tree-0.0.8.dist-info/WHEEL
prefix_tree-0.0.8.dist-info/top_level.txt
prefix_tree-0.0.8.dist-info/RECORD
