Metadata-Version: 2.4
Name: prefix_tree
Version: 0.0.8
Summary: A pure Python prefix tree (trie) for fast in-memory prefix search and filtering
Home-page: https://github.com/ice1x/prefix_tree
Author: ice1x
Author-email: ice2600x@gmale.com
Project-URL: Documentation, https://github.com/ice1x/prefix_tree
Project-URL: Source, https://github.com/ice1x/prefix_tree
Project-URL: Tracker, https://github.com/ice1x/prefix_tree/issues
Classifier: Development Status :: 3 - Alpha
Classifier: Intended Audience :: Developers
Classifier: Topic :: Database
Classifier: Topic :: Software Development :: Libraries
Classifier: Programming Language :: Python :: 3.10
Classifier: Programming Language :: Python :: 3.11
Classifier: License :: OSI Approved :: MIT License
Classifier: Operating System :: OS Independent
Requires-Python: >=3.10
License-File: LICENSE
Dynamic: author
Dynamic: author-email
Dynamic: classifier
Dynamic: description
Dynamic: description-content-type
Dynamic: home-page
Dynamic: license-file
Dynamic: project-url
Dynamic: requires-python
Dynamic: summary
